sdk/__init__.py
sdk/client.py
sdk/core/__init__.py
sdk/core/configs/__init__.py
sdk/core/configs/variables.py
sdk/core/models/__init__.py
sdk/core/models/movie.py
sdk/core/models/quote.py
sdk/core/utils/__init__.py
sdk/core/utils/errors.py
sdk/core/utils/helpers.py
efss_lotrsdk-0.0.2.dist-info/METADATA
efss_lotrsdk-0.0.2.dist-info/WHEEL
efss_lotrsdk-0.0.2.dist-info/top_level.txt
efss_lotrsdk-0.0.2.dist-info/RECORD
